dispider/__init__.py
dispider-3.0.4.dist-info/METADATA
dispider-3.0.4.dist-info/WHEEL
dispider-3.0.4.dist-info/top_level.txt
dispider-3.0.4.dist-info/RECORD
