Metadata-Version: 2.4
Name: dispider
Version: 3.0.4
Summary: A toolkit to help beginners quickly deploy crawlers in batches and manage tasks.
Author: data.dilattice.top
Author-email: 
Keywords: python,spider,dispider,windows,mac,linux
Classifier: Development Status :: 1 - Planning
Classifier: Intended Audience :: Developers
Classifier: Programming Language :: Python :: 3
Classifier: Operating System :: Unix
Classifier: Operating System :: MacOS :: MacOS X
Classifier: Operating System :: Microsoft :: Windows
Requires-Python: >=3.7
Requires-Dist: requests
Requires-Dist: pandas
Dynamic: author
Dynamic: classifier
Dynamic: description
Dynamic: description-content-type
Dynamic: keywords
Dynamic: requires-dist
Dynamic: requires-python
Dynamic: summary
